PyMABSolver/__init__.py
PyMABSolver/main.py
pymabsolver-0.7.dist-info/METADATA
pymabsolver-0.7.dist-info/WHEEL
pymabsolver-0.7.dist-info/top_level.txt
pymabsolver-0.7.dist-info/RECORD
