Metadata-Version: 2.1
Name: pymabsolver
Version: 0.7
Requires-Dist: matplotlib>=3.7.2
